setup.py
py_crypt_keeper_client/__init__.py
py_crypt_keeper_client/cipher.py
py_crypt_keeper_client/client.py
py_crypt_keeper_client/command.py
py_crypt_keeper_client/utility.py
py_crypt_keeper_client.egg-info/PKG-INFO
py_crypt_keeper_client.egg-info/SOURCES.txt
py_crypt_keeper_client.egg-info/dependency_links.txt
py_crypt_keeper_client.egg-info/entry_points.txt
py_crypt_keeper_client.egg-info/not-zip-safe
py_crypt_keeper_client.egg-info/requires.txt
py_crypt_keeper_client.egg-info/top_level.txt