Metadata-Version: 1.0
Name: py-crypt-keeper-client
Version: 0.1
Summary: A Python client for the Crypt-Keeper service.
Home-page: http://github.com/mauricecarey/py_crypt_keeper_client
Author: Maurice Carey
Author-email: maurice@mauricecarey.com
License: Apache License, Version 2.0
Platform: UNKNOWN
